GPViz-0.0.4.dist-info/DESCRIPTION.rst
GPViz-0.0.4.dist-info/METADATA
GPViz-0.0.4.dist-info/RECORD
GPViz-0.0.4.dist-info/WHEEL
GPViz-0.0.4.dist-info/metadata.json
GPViz-0.0.4.dist-info/top_level.txt
gpviz/__init__.py
gpviz/gp.py
gpviz/install.py
gpviz/kernel.py
gpviz/utils.py
gpviz/styles/__init__.py
gpviz/styles/colours.py
